cape_parsers/CAPE/__init__.py
cape_parsers/CAPE/community/AgentTesla.py
cape_parsers/CAPE/community/Amadey.py
cape_parsers/CAPE/community/Amatera.py
cape_parsers/CAPE/community/Arkei.py
cape_parsers/CAPE/community/AsyncRAT.py
cape_parsers/CAPE/community/AuroraStealer.py
cape_parsers/CAPE/community/Carbanak.py
cape_parsers/CAPE/community/CobaltStrikeBeacon.py
cape_parsers/CAPE/community/CobaltStrikeStager.py
cape_parsers/CAPE/community/DCRat.py
cape_parsers/CAPE/community/Fareit.py
cape_parsers/CAPE/community/KoiLoader.py
cape_parsers/CAPE/community/LokiBot.py
cape_parsers/CAPE/community/Lumma.py
cape_parsers/CAPE/community/MonsterV2.py
cape_parsers/CAPE/community/MyKings.py
cape_parsers/CAPE/community/NanoCore.py
cape_parsers/CAPE/community/Nighthawk.py
cape_parsers/CAPE/community/Njrat.py
cape_parsers/CAPE/community/PhemedroneStealer.py
cape_parsers/CAPE/community/QuasarRAT.py
cape_parsers/CAPE/community/README.md
cape_parsers/CAPE/community/Snake.py
cape_parsers/CAPE/community/SparkRAT.py
cape_parsers/CAPE/community/Stealc.py
cape_parsers/CAPE/community/VenomRAT.py
cape_parsers/CAPE/community/WinosStager.py
cape_parsers/CAPE/community/XWorm.py
cape_parsers/CAPE/community/XenoRAT.py
cape_parsers/CAPE/community/__init__.py
cape_parsers/CAPE/core/AdaptixBeacon.py
cape_parsers/CAPE/core/AuraStealer.py
cape_parsers/CAPE/core/Azorult.py
cape_parsers/CAPE/core/BitPaymer.py
cape_parsers/CAPE/core/BlackDropper.py
cape_parsers/CAPE/core/Blister.py
cape_parsers/CAPE/core/BruteRatel.py
cape_parsers/CAPE/core/BumbleBee.py
cape_parsers/CAPE/core/DarkGate.py
cape_parsers/CAPE/core/DoppelPaymer.py
cape_parsers/CAPE/core/DridexLoader.py
cape_parsers/CAPE/core/Formbook.py
cape_parsers/CAPE/core/GuLoader.py
cape_parsers/CAPE/core/IcedID.py
cape_parsers/CAPE/core/IcedIDLoader.py
cape_parsers/CAPE/core/Latrodectus.py
cape_parsers/CAPE/core/NitroBunnyDownloader.py
cape_parsers/CAPE/core/Oyster.py
cape_parsers/CAPE/core/PikaBot.py
cape_parsers/CAPE/core/PlugX.py
cape_parsers-0.1.61.dist-info/METADATA
cape_parsers-0.1.61.dist-info/WHEEL
cape_parsers-0.1.61.dist-info/licenses/LICENSE
cape_parsers-0.1.61.dist-info/RECORD
